{"408_2009.md":"Do1tUZk0","408_2010.md":"nB9bWAen","408_2011.md":"BRm-XD6Y","408_2012.md":"4DIycrxC","408_2013.md":"DTeARRxQ","408_2014.md":"CG7QhfiS","408_2015.md":"D7KKoTUL","408_2016.md":"DLrIuVQh","408_2017.md":"BE-NKHcS","408_2018.md":"BUVvo3sV","408_2019.md":"CoR2m91g","algorithm_lru.md":"cDBGynGZ","algorithm_退避算法.md":"Dpg33FvE","architecture_base.md":"C9Kv6efU","architecture_iconfont.md":"DJk2tqBT","architecture_jp架构.md":"VAmQ_xvz","browser_ introduce.md":"BJIFKLcj","browser_async_await.md":"D9nic-vu","browser_chrome开发者工具.md":"D9uIW-Rj","browser_chrome架构.md":"Ci__jtZ7","browser_csrf攻击.md":"DjKlPeOs","browser_dom树.md":"PIUb7wvj","browser_http.md":"COcO4Vux","browser_http1.md":"CMAPpvov","browser_http2.md":"D1hyXK6A","browser_http3.md":"BupkPkee","browser_https.md":"D1n-SHI8","browser_performance.md":"vn9zDjKJ","browser_performance中的main指标.md":"C_Gs0kyj","browser_promise.md":"DFYjNJT4","browser_renderfirst.md":"D2trTdvH","browser_rendersec.md":"3ZxMMbNG","browser_settimeout如何实现.md":"lVRo50lu","browser_tcp协议.md":"rEUDq1-l","browser_this.md":"l4rOp-Fx","browser_xmlhttprequest.md":"DYi_fBKS","browser_任务调度.md":"9qWkH9dv","browser_作用域链和闭包.md":"B4-3Hzez","browser_分层和合成.md":"BhY_c0e5","browser_加载阶段性能.md":"D9ZBrCrs","browser_变量提升.md":"BZA-p9rt","browser_同源策略.md":"Dcgo0v_z","browser_块级作用域.md":"4kApESyY","browser_垃圾回收.md":"erVwHNKV","browser_安全沙箱.md":"BStrXmdI","browser_宏任务和微任务.md":"BKBfdBdr","browser_导航流程.md":"DZd0m-Dp","browser_栈和堆.md":"3TS9SKFp","browser_浏览上下文组.md":"_sMyV974","browser_消息队列和事件循环.md":"D08SITy5","browser_渐进式网页应用pwa.md":"CR-wkmVm","browser_渲染流水线.md":"CBjYEgKf","browser_编译器和解释器.md":"Bn3oYj9H","browser_虚拟dom.md":"BfUEgvA2","browser_调用栈.md":"B5ytWHRO","browser_跨站脚本攻击xss.md":"DDuWMz3n","browser_页面性能.md":"CnSsL4yL","datastructure_chapter1.md":"UensgjAm","datastructure_chapter1_ex.md":"MJJw230T","datastructure_chapter2.md":"DGm68WWT","datastructure_chapter2_ex.md":"BPeJ-RmL","datastructure_chapter3.md":"7ZacNeHj","datastructure_chapter4.md":"lEtqOvr8","datastructure_chapter5.md":"BjypEzeI","datastructure_chapter6.md":"C7uFguAJ","datastructure_chapter7.md":"BPBu8VIz","datastructure_chapter8.md":"C1oBaQBD","datastructure_强化.md":"BVVDYdgY","docs_hello.md":"COj6-58i","index.md":"ndRlxEzi","interview_browser.md":"Dl9sYFhD","interview_coding.md":"WUdaREz1","interview_css.md":"Cb3cDgmn","interview_html.md":"n5lOwwV_","interview_js.md":"C4SgRpn_","interview_network.md":"B3EWf41Z","interview_project.md":"Cs28OKLB","interview_react.md":"85ORgDgU","interview_typescript.md":"BIfSWblY","interview_webpack.md":"OK3ehHNh","javascript_advance_browser.md":"DkDD-jGm","javascript_advance_execution.md":"DNEjgCD9","javascript_advance_executioncontext.md":"C4pJNqTg","javascript_advance_executionstack.md":"CbmjDonk","javascript_basic_你不知道的js.md":"B7SphomR","mine_about.md":"CIDH0XV_","mine_resume.md":"D_DzbzUK","mine_resume_fudan.md":"C-p9r1SL","mobile_pha.md":"DQUcMB7x","nav_index.md":"DcVFmsHJ","os_chapter1.md":"swdB5HaX","os_chapter2.md":"fQ-MMAkH","os_chapter3.md":"TJXIGToX","os_chapter4.md":"C3hYHi48","os_chapter5.md":"DP53bhqg","os_强化.md":"0tWCGs0l","postgraduate_school.md":"7thy-vh0","posts_communicationmechanisms.md":"rA42TSfC","posts_dataprefetch.md":"BBENDY1-","posts_im多端一致性.md":"DJ6y2q3F","posts_index.md":"DvMmWN9L","posts_rendermode.md":"80v_AfF0","posts_rpxtovw.md":"BwykzCvi","posts_skelon.md":"p6qtY__a","posts_uno-css-jp.md":"Cj3QqRFm","posts_埋点.md":"DVFZa78i","posts_性能优化.md":"Bz2yJT2f","project_aem.md":"BGzzzKiu","project_component_ssr.md":"Dq9FC3Py","project_cross_border.md":"BdvX7sve","project_generate_icon.md":"B5_-6llH","project_index.md":"ZZAoOeQf","project_lerna_monorepo.md":"BCO3a9B1","project_linyang.md":"DDTCPlx0","project_local_return.md":"B1KqR_2O","project_odin_document.md":"DY_auabg","project_react-intl.md":"Dj5YlQYs","project_ssr_operate.md":"C2S3n0Ur","project_taojp.md":"QRjpqkQq","project_tmm_architecture.md":"CgSvmFGY","project_tmm_index.md":"BZkWsv0s","project_tmm_local_search.md":"CvmYfV4-","project_tmm_mention.md":"kc91XI6j","project_tmm_partfileupload.md":"CoimmWuG","project_tmm_performance_optimization.md":"ymH3aFLo","project_tmm_rbac.md":"DjaWmugq","project_tmm_resources_manner.md":"DxPUezkc","react_core_basestruct.md":"DwarTRGy","react_core_basic.md":"DwblnfH2","react_core_innercore.md":"3zathczk","react_core_前端ui框架简史.md":"CbtxMNIC","react_core_核心原理.md":"CL9myBtf","react_core_设计理念.md":"BGBwmFD1","react_customhook_hooks.md":"B4uG3dtH","react_record_thinking.md":"gQdArgFv","react_utils_type.md":"Bxs02jyX","record_amap.md":"ZfxtKwa6","record_nvm.md":"CNLNNdsn","record_tallking.md":"CagWMAVe","test.md":"_jpSY386","todo_2025.md":"BqIKrqwj","todo_index.md":"BBJDVk--","typescript_costums.md":"DjLgQwlY","typescript_记录.md":"C3Brd1Uf","utils_throttle.md":"0CWgvb4P","utils_utils.md":"D9B24QHw","vue_basic.md":"CLHLAaCi","webpack_performance.md":"Dh_r6A8a","webpack_unocss.md":"Bla6Rf1o","webpack_埋点.md":"BKDCGhZ5","welcome.md":"BbvqWCWu","组成原理_chapter1.md":"CzYdO86M","组成原理_chapter2.md":"BmeVzgRC","组成原理_chapter3.md":"CxKs5H_U","组成原理_chapter4.md":"BOqgxpz5","组成原理_chapter5.md":"CCahwqHx","组成原理_chapter6.md":"BMqfgs4K","组成原理_chapter7.md":"DKEEdFAv","组成原理_强化.md":"BEqxeBN_","计网_chapter1.md":"DWuEGmYo","计网_chapter2.md":"DWs1b6Cy","计网_chapter3.md":"Bw3Jtv7N","计网_https.md":"XOe9jzFm","计网_websocket.md":"BjEszD_D","计网_强化.md":"CnNpR8y2"}
