{"architecture_base.md":"Ci-iERLM","javascript_advance_browser.md":"C0vUJMwn","408_2010.md":"DLyWsdm5","408_2018.md":"BhObJ4qS","browser_http3.md":"DOkfxlge","browser_xmlhttprequest.md":"BBXjuDBz","browser_renderfirst.md":"Ck0jIHvo","browser_rendersec.md":"CrncNfkj","browser_settimeout如何实现.md":"B_AakyZY","todo_2025.md":"BiEFKj0I","vue_basic.md":"Bio5oO-F","browser_async_await.md":"DCw5BcLG","todo_index.md":"BpUBnCGX","408_2015.md":"BQ798TVo","408_2009.md":"2VbdvagB","browser_chrome开发者工具.md":"B_7g98pj","browser_performance.md":"BsGca_jB","architecture_jp架构.md":"BHCDF8AB","408_2012.md":"C-eQEIGb","browser_tcp协议.md":"CMAW8k9G","postgraduate_school.md":"DZe2KIT6","browser_http.md":"DWA2fezt","browser_http1.md":"3DqVq762","408_2016.md":"CVSTdnZQ","browser_performance中的main指标.md":"BBRmiRXm","408_2011.md":"ekY91YMP","408_2019.md":"q9AurkSA","browser_promise.md":"BfDyvCg_","browser_https.md":"BbLOz3pc","browser_csrf攻击.md":"DTtZ_e87","architecture_iconfont.md":"nU-J2ovU","javascript_advance_executionstack.md":"BnvFsaAu","javascript_basic_你不知道的js.md":"BZ60Fk2L","javascript_advance_execution.md":"Bh20Vp4H","browser_chrome架构.md":"BzfQ_QPZ","408_2013.md":"FcGusKNV","datastructure_chapter2_ex.md":"C7CTdNfO","browser_垃圾回收.md":"DvOcdtgq","browser_安全沙箱.md":"1DY_gzcs","browser_导航流程.md":"D5pUImVV","browser_浏览上下文组.md":"DEHOdvLj","browser_消息队列和事件循环.md":"BW2uEJT8","datastructure_chapter1_ex.md":"BL5vloSO","browser_作用域链和闭包.md":"BbAESXJ6","browser_渐进式网页应用pwa.md":"CzyHWSGz","browser_加载阶段性能.md":"Cgv0y_Mu","browser_变量提升.md":"CsvPjOAV","javascript_advance_executioncontext.md":"BxvDROxy","browser_调用栈.md":"F1as1v-3","browser_栈和堆.md":"0M7xweVY","browser_页面性能.md":"ucMSxadT","408_2017.md":"CePa9TMx","browser_ introduce.md":"DlomH7jB","browser_分层和合成.md":"CpIZEzfB","408_2014.md":"BXmFKIVt","browser_跨站脚本攻击xss.md":"Su0n5QsI","browser_http2.md":"BDC6ZWX6","browser_渲染流水线.md":"CXw92fg_","datastructure_chapter2.md":"9Ydea7cR","browser_任务调度.md":"BNNvng6r","browser_块级作用域.md":"C85hu1y4","browser_同源策略.md":"Dpq2i_pq","datastructure_chapter1.md":"DMItT4wl","browser_this.md":"CHPmB-_w","mobile_pha.md":"CnJSH5QF","datastructure_chapter4.md":"BqjEO9iX","interview_css.md":"V1BUCjqK","interview_browser.md":"n2bdMGiX","browser_虚拟dom.md":"DunG3MIG","browser_编译器和解释器.md":"Dn-VCFiE","browser_宏任务和微任务.md":"DkLqBMIo","browser_dom树.md":"CDfJbFl1","datastructure_chapter7.md":"BN0l65Rp","datastructure_chapter3.md":"DUR1WyjH","interview_html.md":"CE45tvOD","docs_hello.md":"DtkAFhUR","interview_project.md":"SePxsYDx","datastructure_chapter5.md":"B7uGTaGM","interview_react.md":"QdXhMHDS","react_core_前端ui框架简史.md":"DOEw66dR","nav_index.md":"Ck7vIg4f","os_chapter1.md":"DK_gzIZA","os_chapter5.md":"0K08x_ki","react_record_thinking.md":"_3sqF1OF","datastructure_强化.md":"sdlbXYKe","typescript_costums.md":"B__cDoix","record_nvm.md":"KfXM6OCD","index.md":"C9PANpb2","os_强化.md":"ChBsBVbY","posts_csr_ssr_ssg.md":"C_dRAK8U","posts_reimagine-atomic-css.md":"DjTSIlPx","interview_webpack.md":"-Bcqf521","interview_js.md":"DgOxON88","react_utils_type.md":"DxBkvgxq","welcome.md":"_pyk8yOH","webpack_埋点.md":"CYIB6Y_d","组成原理_chapter1.md":"CNies1jh","posts_skelon.md":"DfmfmMF-","组成原理_chapter5.md":"BahPiD_4","组成原理_chapter2.md":"BmnBz7ma","组成原理_chapter7.md":"Bcn4-3Lt","组成原理_chapter6.md":"BooUDrCT","组成原理_chapter4.md":"CyrBJ9a1","计网_chapter2.md":"Zvhf73m9","posts_performance-flag.md":"CksIKwmk","组成原理_chapter3.md":"ezE0WAb5","计网_chapter3.md":"Bq4PQskG","计网_强化.md":"D8B0qNnd","typescript_记录.md":"CxkuGEdK","计网_https.md":"Bwex0AR_","os_chapter3.md":"Di9fvqdT","interview_network.md":"Cw3EAr_v","react_customhook_hooks.md":"BRJajaHb","test.md":"fi6TLgn2","react_core_innercore.md":"B2vKpcun","utils_utils.md":"BGjBO8fP","webpack_unocss.md":"BEXpJARr","计网_chapter1.md":"BlHdkb27","datastructure_chapter6.md":"B268Rfnu","interview_coding.md":"BITuYqez","record_amap.md":"CE4y0pU0","record_tallking.md":"D6WuWj_U","project_component_ssr.md":"DgIw24ff","project_cross_border.md":"CIBM5q-B","project_index.md":"izIxAXby","project_odin_document.md":"DrmLtOcs","project_local_return.md":"BapulCKe","project_react-intl.md":"CONmUr_p","project_generate_icon.md":"CRgA50NW","project_lerna_monorepo.md":"CBkofY0B","interview_typescript.md":"DWzsxhVN","react_core_核心原理.md":"OBYNhesJ","posts_rendermode.md":"FfWoV509","组成原理_强化.md":"BngmkqWf","posts_性能优化.md":"BFr17PWw","os_chapter4.md":"C0k6q52D","react_core_设计理念.md":"BzU6bn94","os_chapter2.md":"C3j8kc9L","datastructure_chapter8.md":"B5UfN8Ck","posts_uno-css-jp.md":"BTIVo5A4","posts_埋点.md":"BKFzWyNT","project_ssr_operate.md":"Cbf63kII","project_taojp.md":"BfxrbG1K","react_core_basic.md":"hkdwlWhA","react_core_basestruct.md":"rMwgNlqa","webpack_performance.md":"CftaNsHl"}
